functions/__init__.py
functions/__main__.py
functions/actions.py
functions/autocomplete.py
functions/callbacks.py
functions/cloud.py
functions/commands/__init__.py
functions/commands/components/__init__.py
functions/commands/components/docker.py
functions/commands/components/gcp.py
functions/commands/gcp.py
functions/commands/new.py
functions/commands/sync.py
functions/components/__init__.py
functions/components/docker.py
functions/components/errors.py
functions/components/gcp.py
functions/config/constants.py
functions/config/enums.py
functions/config/errors.py
functions/config/files.py
functions/config/interfaces.py
functions/config/managers.py
functions/config/models.py
functions/config/types.py
functions/constants.py
functions/core.py
functions/decorators.py
functions/defaults.py
functions/docker/__init__.py
functions/docker/api.py
functions/docker/enums.py
functions/docker/helpers.py
functions/docker/models.py
functions/docker/types.py
functions/error_handlers.py
functions/errors.py
functions/flows.py
functions/gcp/autocomplete.py
functions/gcp/callbacks.py
functions/gcp/cloud_function/__init__.py
functions/gcp/cloud_function/cli.py
functions/gcp/cloud_function/constants.py
functions/gcp/cloud_function/defaults.py
functions/gcp/cloud_function/errors.py
functions/gcp/cloud_function/models.py
functions/gcp/cloud_run/__init__.py
functions/gcp/cloud_run/models.py
functions/gcp/constants.py
functions/gcp/defaults.py
functions/gcp/errors.py
functions/gcp/helpers.py
functions/gcp/services.py
functions/helpers.py
functions/logs.py
functions/main.py
functions/models.py
functions/processes.py
functions/protocols.py
functions/styles.py
functions/system.py
functions/types.py
functions/user.py
functions/validators.py
functions_cli-0.1.0.dist-info/entry_points.txt
functions_cli-0.1.0.dist-info/LICENSE
functions_cli-0.1.0.dist-info/WHEEL
functions_cli-0.1.0.dist-info/METADATA
functions_cli-0.1.0.dist-info/RECORD
