Metadata-Version: 2.1
Name: functions-cli
Version: 0.1.0
Summary: CLI tool for managing local and cross-cloud FaaS serverless resources
Home-page: https://katolus.github.io/functions/
License: MIT
Keywords: serverless,cloud function,functions,faas,faas-cli
Author: Piotr Katolik
Author-email: katolus@ventress.org
Requires-Python: >=3.7,<4.0
Classifier: Development Status :: 3 - Alpha
Classifier: Environment :: Console
Classifier: Intended Audience :: Developers
Classifier: License :: OSI Approved :: MIT License
Classifier: Natural Language :: English
Classifier: Operating System :: MacOS
Classifier: Operating System :: Microsoft
Classifier: Operating System :: OS Independent
Classifier: Operating System :: POSIX :: Linux
Classifier: Programming Language :: Python :: 3
Classifier: Programming Language :: Python :: 3.10
Classifier: Programming Language :: Python :: 3.11
Classifier: Programming Language :: Python :: 3.7
Classifier: Programming Language :: Python :: 3.8
Classifier: Programming Language :: Python :: 3.9
Classifier: Topic :: System :: Distributed Computing
Classifier: Topic :: Terminals
Classifier: Topic :: Utilities
Requires-Dist: docker (>=5.0.2,<6.0.0)
Requires-Dist: pydantic (>=1.8.2,<2.0.0)
Requires-Dist: toml (>=0.10.2,<0.11.0)
Requires-Dist: typer (>=0.3.0,<0.4.0)
Project-URL: Documentation, https://katolus.github.io/functions/
Project-URL: Repository, https://github.com/Katolus/functions
